git_notes_memory/__init__.py
git_notes_memory/capture.py
git_notes_memory/config.py
git_notes_memory/embedding.py
git_notes_memory/exceptions.py
git_notes_memory/git_ops.py
git_notes_memory/index.py
git_notes_memory/lifecycle.py
git_notes_memory/main.py
git_notes_memory/models.py
git_notes_memory/note_parser.py
git_notes_memory/patterns.py
git_notes_memory/recall.py
git_notes_memory/registry.py
git_notes_memory/search.py
git_notes_memory/sync.py
git_notes_memory/utils.py
git_notes_memory/hooks/__init__.py
git_notes_memory/hooks/capture_decider.py
git_notes_memory/hooks/config_loader.py
git_notes_memory/hooks/context_builder.py
git_notes_memory/hooks/domain_extractor.py
git_notes_memory/hooks/guidance_builder.py
git_notes_memory/hooks/hook_utils.py
git_notes_memory/hooks/models.py
git_notes_memory/hooks/namespace_parser.py
git_notes_memory/hooks/namespace_styles.py
git_notes_memory/hooks/novelty_checker.py
git_notes_memory/hooks/post_tool_use_handler.py
git_notes_memory/hooks/pre_compact_handler.py
git_notes_memory/hooks/project_detector.py
git_notes_memory/hooks/session_analyzer.py
git_notes_memory/hooks/session_start_handler.py
git_notes_memory/hooks/signal_detector.py
git_notes_memory/hooks/stop_handler.py
git_notes_memory/hooks/user_prompt_handler.py
git_notes_memory/hooks/xml_formatter.py
git_notes_memory/observability/__init__.py
git_notes_memory/observability/config.py
git_notes_memory/observability/decorators.py
git_notes_memory/observability/logging.py
git_notes_memory/observability/metrics.py
git_notes_memory/observability/session.py
git_notes_memory/observability/tracing.py
git_notes_memory/observability/exporters/__init__.py
git_notes_memory/observability/exporters/json_exporter.py
git_notes_memory/observability/exporters/otlp.py
git_notes_memory/observability/exporters/prometheus.py
git_notes_memory/security/__init__.py
git_notes_memory/security/allowlist.py
git_notes_memory/security/audit.py
git_notes_memory/security/config.py
git_notes_memory-0.12.0.dist-info/METADATA
git_notes_memory-0.12.0.dist-info/WHEEL
git_notes_memory-0.12.0.dist-info/entry_points.txt
git_notes_memory-0.12.0.dist-info/licenses/LICENSE
git_notes_memory-0.12.0.dist-info/RECORD
