Metadata-Version: 2.4
Name: git-notes-memory
Version: 0.12.0
Summary: Git-native, semantically-searchable memory storage for Claude Code
Project-URL: Homepage, https://github.com/zircote/git-notes-memory
Project-URL: Documentation, https://github.com/zircote/git-notes-memory#readme
Project-URL: Repository, https://github.com/zircote/git-notes-memory.git
Project-URL: Bug Tracker, https://github.com/zircote/git-notes-memory/issues
License: MIT
License-File: LICENSE
Keywords: claude-code,embeddings,git,memory,notes,semantic-search
Classifier: Development Status :: 3 - Alpha
Classifier: Intended Audience :: Developers
Classifier: License :: OSI Approved :: MIT License
Classifier: Programming Language :: Python :: 3
Classifier: Programming Language :: Python :: 3.11
Classifier: Programming Language :: Python :: 3.12
Classifier: Programming Language :: Python :: 3.13
Classifier: Topic :: Software Development :: Libraries :: Python Modules
Classifier: Topic :: Software Development :: Version Control :: Git
Classifier: Typing :: Typed
Requires-Python: >=3.11
Requires-Dist: detect-secrets>=1.4.0
Requires-Dist: python-dotenv>=1.0.1
Requires-Dist: pyyaml>=6.0.2
Requires-Dist: sentence-transformers>=3.0.0
Requires-Dist: sqlite-vec>=0.1.6
Provides-Extra: dev
Requires-Dist: bandit>=1.8.0; extra == 'dev'
Requires-Dist: build>=1.2.0; extra == 'dev'
Requires-Dist: bump-my-version>=1.1.0; extra == 'dev'
Requires-Dist: mypy>=1.19.0; extra == 'dev'
Requires-Dist: pip-audit>=2.9.0; extra == 'dev'
Requires-Dist: pytest-asyncio>=1.0.0; extra == 'dev'
Requires-Dist: pytest-cov>=7.0.0; extra == 'dev'
Requires-Dist: pytest>=9.0.2; extra == 'dev'
Requires-Dist: ruff>=0.14.0; extra == 'dev'
Requires-Dist: types-pyyaml>=6.0.12; extra == 'dev'
